{
  "_fv": 13,
  "_type": "tool",
  "definition": {
    "renderType": 0,
    "texture": "placeholder_hoe",
    "customModelName": "Normal",
    "name": "Placeholder Hoe",
    "specialInfo": [],
    "creativeTab": {
      "value": "COMBAT"
    },
    "toolType": "Hoe",
    "harvestLevel": 10,
    "efficiency": 10.0,
    "attackSpeed": 10.0,
    "enchantability": 100,
    "damageVsEntity": 100.0,
    "usageCount": 1000,
    "blocksAffected": [],
    "hasGlow": false,
    "repairItems": [
      {
        "value": "CUSTOM:PlaceholderIngot"
      }
    ],
    "stayInGridWhenCrafting": false,
    "damageOnCrafting": false
  }
}